{
  "id": "2f9795cd-7e7d-453e-96e5-228f36a03fd1",
  "title": "テスト記事",
  "thumbnail": {
    "id": "535c8105-fd92-47b7-93ce-dc01b379ae66",
    "path": "test-book"
  },
  "postDate": "2021-01-01",
  "lastUpdateDate": "2021-01-02",
  "contents": [
    {
      "id": "89dd635c-66d7-4290-a641-8740369a8751",
      "text": [
        { "text": "これはテスト用の文字列です。", "styles": { "bold": true } }
      ],
      "type": "paragraph"
    },
    {
      "id": "5112f0e0-7593-4925-a29f-42645c0468f2",
      "text": "見出しレベル2",
      "type": "h2"
    },
    {
      "id": "aa6dda82-6d29-471e-a68a-0303d1b9bb03",
      "text": "見出しレベル3",
      "type": "h3"
    }
  ]
}
